MANIFEST.in
README.rst
setup.cfg
setup.py
bidict/VERSION
bidict/__init__.py
bidict/_bidict.py
bidict/_common.py
bidict/_frozen.py
bidict/_loose.py
bidict/_named.py
bidict/_ordered.py
bidict/compat.py
bidict/util.py
bidict_knaperek.egg-info/PKG-INFO
bidict_knaperek.egg-info/SOURCES.txt
bidict_knaperek.egg-info/dependency_links.txt
bidict_knaperek.egg-info/requires.txt
bidict_knaperek.egg-info/top_level.txt
bidict_knaperek.egg-info/zip-safe