Metadata-Version: 1.1
Name: bidict-knaperek
Version: 0.13.1
Summary: Efficient, Pythonic bidirectional map implementation and related functionality
Home-page: https://github.com/jab/bidict
Author: Joshua Bronson
Author-email: jab@math.brown.edu
License: ISC
Keywords: dict,dictionary,mapping,bidirectional,bijection,bijective,injective,two-way,2-way,double,inverse,reverse
Platform: UNKNOWN
Classifier: Development Status :: 4 - Beta
Classifier: Intended Audience :: Developers
Classifier: License :: OSI Approved :: ISC License (ISCL)
Classifier: Natural Language :: English
Classifier: Operating System :: OS Independent
Classifier: Programming Language :: Python :: 2.7
Classifier: Programming Language :: Python :: 3
Classifier: Programming Language :: Python :: 3.4
Classifier: Programming Language :: Python :: 3.5
Classifier: Programming Language :: Python :: 3.6
Classifier: Programming Language :: Python :: Implementation :: CPython
Classifier: Programming Language :: Python :: Implementation :: PyPy
Classifier: Topic :: Scientific/Engineering :: Mathematics
Classifier: Topic :: Software Development :: Libraries :: Python Modules
